certi_builder/__init__.py
certi_builder/__main__.py
certi_builder/builder.py
certi_builder-1.0.1.dist-info/LICENSE
certi_builder-1.0.1.dist-info/METADATA
certi_builder-1.0.1.dist-info/WHEEL
certi_builder-1.0.1.dist-info/dependency_links.txt
certi_builder-1.0.1.dist-info/entry_points.txt
certi_builder-1.0.1.dist-info/top_level.txt
certi_builder-1.0.1.dist-info/RECORD
