Metadata-Version: 2.1
Name: certi-builder
Version: 1.0.1
Summary: A simple commandline app for generating bulk of certificates
Home-page: https://github.com/Horizon733/certi-build
Author: Dishant Gandhi
Author-email: dishantgandhi733@gmail.com
License: MIT
Download-URL: https://github.com/Horizon733/certi-build/archive/refs/tags/v1.0.1.tar.gz
Platform: UNKNOWN
Classifier: License :: OSI Approved :: MIT License
Classifier: Programming Language :: Python :: 3
Classifier: Programming Language :: Python :: 3.7
Requires-Python: >=3.7, <3.9
License-File: LICENSE
Requires-Dist: pandas
Requires-Dist: Pillow
Requires-Dist: twine
Requires-Dist: click
Requires-Dist: openpyxl
